{
  "last_update": "2026-07-11T14:13:56.545Z",
  "total_sites": 34,
  "failed_count": 1,
  "data": [
    {
      "url": "https://hotstreakcasino-uk.net",
      "status": 200,
      "ok": true,
      "duration": 303
    },
    {
      "url": "https://tradacasino-uk.net",
      "status": 200,
      "ok": true,
      "duration": 421
    },
    {
      "url": "https://truefortune-go.com",
      "status": 200,
      "ok": true,
      "duration": 457
    },
    {
      "url": "https://freshbet-uk.org",
      "status": 200,
      "ok": true,
      "duration": 483
    },
    {
      "url": "https://slotscharmcasino.org.uk",
      "status": 503,
      "ok": false,
      "duration": 556
    },
    {
      "url": "https://winbeastcasino.gb.net",
      "status": 503,
      "ok": false,
      "duration": 613
    },
    {
      "url": "https://slotlaircasino.gb.net",
      "status": 503,
      "ok": false,
      "duration": 581
    },
    {
      "url": "https://britsinocasino.gb.net",
      "status": 503,
      "ok": false,
      "duration": 652
    },
    {
      "url": "https://slotscharm-casino.org.uk",
      "status": 200,
      "ok": true,
      "duration": 688
    },
    {
      "url": "https://hotstreak-casino.gb.net",
      "status": 503,
      "ok": false,
      "duration": 731
    },
    {
      "url": "https://true-fortune-casino.gb.net",
      "status": 503,
      "ok": false,
      "duration": 771
    },
    {
      "url": "https://prestigespin-casino.org.uk",
      "status": 503,
      "ok": false,
      "duration": 777
    },
    {
      "url": "https://freshbetcasino.gb.net",
      "status": 503,
      "ok": false,
      "duration": 806
    },
    {
      "url": "https://instaspin-casino.gb.net",
      "status": 503,
      "ok": false,
      "duration": 836
    },
    {
      "url": "https://instaspin7.com",
      "status": 200,
      "ok": true,
      "duration": 873
    },
    {
      "url": "https://truefortune7.co.uk",
      "status": 503,
      "ok": false,
      "duration": 908
    },
    {
      "url": "https://truefortune-casino.gb.net",
      "status": 503,
      "ok": false,
      "duration": 912
    },
    {
      "url": "https://insta-spin.gb.net",
      "status": 503,
      "ok": false,
      "duration": 959
    },
    {
      "url": "https://instaspin-win.co.uk",
      "status": 503,
      "ok": false,
      "duration": 1088
    },
    {
      "url": "https://tradacasino-go.co.uk",
      "status": 200,
      "ok": true,
      "duration": 1089
    },
    {
      "url": "https://slotscharmcasino.gb.net",
      "status": 503,
      "ok": false,
      "duration": 1162
    },
    {
      "url": "https://slotlair-casino.gb.net",
      "status": 503,
      "ok": false,
      "duration": 1171
    },
    {
      "url": "https://britsino.gb.net",
      "status": 503,
      "ok": false,
      "duration": 1189
    },
    {
      "url": "https://winbeast-casino.gb.net",
      "status": 503,
      "ok": false,
      "duration": 1235
    },
    {
      "url": "https://slotlaircasino-uk.org",
      "status": 200,
      "ok": true,
      "duration": 1252
    },
    {
      "url": "https://hotstreakcasino-uk.org",
      "status": 200,
      "ok": true,
      "duration": 55
    },
    {
      "url": "https://this-domain-is-fake-and-dead.com",
      "status": "ERROR",
      "ok": false,
      "error": "fetch failed"
    },
    {
      "url": "https://prestigespincasino.gb.net",
      "status": 503,
      "ok": false,
      "duration": 499
    },
    {
      "url": "https://freshbet-casino.gb.net",
      "status": 503,
      "ok": false,
      "duration": 539
    },
    {
      "url": "https://fresh-bet.gb.net",
      "status": 503,
      "ok": false,
      "duration": 563
    },
    {
      "url": "https://betnjet.gb.net",
      "status": 503,
      "ok": false,
      "duration": 594
    },
    {
      "url": "https://vibro-bet.gb.net",
      "status": 503,
      "ok": false,
      "duration": 597
    },
    {
      "url": "https://hustlescasino.gb.net",
      "status": 503,
      "ok": false,
      "duration": 599
    },
    {
      "url": "https://hotstreak-casino.org.uk",
      "status": 503,
      "ok": false,
      "duration": 642
    }
  ]
}