{
  "last_update": "2026-07-09T15:48:39.268Z",
  "total_sites": 34,
  "failed_count": 1,
  "data": [
    {
      "url": "https://slotscharmcasino.org.uk",
      "status": 503,
      "ok": false,
      "duration": 434
    },
    {
      "url": "https://britsinocasino.gb.net",
      "status": 503,
      "ok": false,
      "duration": 435
    },
    {
      "url": "https://winbeastcasino.gb.net",
      "status": 503,
      "ok": false,
      "duration": 504
    },
    {
      "url": "https://slotlaircasino.gb.net",
      "status": 503,
      "ok": false,
      "duration": 444
    },
    {
      "url": "https://freshbet-uk.org",
      "status": 200,
      "ok": true,
      "duration": 442
    },
    {
      "url": "https://prestigespin-casino.org.uk",
      "status": 503,
      "ok": false,
      "duration": 483
    },
    {
      "url": "https://instaspin7.com",
      "status": 200,
      "ok": true,
      "duration": 520
    },
    {
      "url": "https://tradacasino-uk.net",
      "status": 200,
      "ok": true,
      "duration": 534
    },
    {
      "url": "https://hotstreak-casino.gb.net",
      "status": 503,
      "ok": false,
      "duration": 567
    },
    {
      "url": "https://slotscharm-casino.org.uk",
      "status": 503,
      "ok": false,
      "duration": 572
    },
    {
      "url": "https://truefortune-go.com",
      "status": 200,
      "ok": true,
      "duration": 655
    },
    {
      "url": "https://hotstreakcasino-uk.net",
      "status": 503,
      "ok": false,
      "duration": 678
    },
    {
      "url": "https://true-fortune-casino.gb.net",
      "status": 503,
      "ok": false,
      "duration": 683
    },
    {
      "url": "https://freshbetcasino.gb.net",
      "status": 503,
      "ok": false,
      "duration": 745
    },
    {
      "url": "https://instaspin-casino.gb.net",
      "status": 503,
      "ok": false,
      "duration": 746
    },
    {
      "url": "https://truefortune7.co.uk",
      "status": 503,
      "ok": false,
      "duration": 847
    },
    {
      "url": "https://truefortune-casino.gb.net",
      "status": 503,
      "ok": false,
      "duration": 874
    },
    {
      "url": "https://instaspin-win.co.uk",
      "status": 503,
      "ok": false,
      "duration": 976
    },
    {
      "url": "https://slotlair-casino.gb.net",
      "status": 503,
      "ok": false,
      "duration": 982
    },
    {
      "url": "https://insta-spin.gb.net",
      "status": 503,
      "ok": false,
      "duration": 994
    },
    {
      "url": "https://tradacasino-go.co.uk",
      "status": 503,
      "ok": false,
      "duration": 998
    },
    {
      "url": "https://winbeast-casino.gb.net",
      "status": 503,
      "ok": false,
      "duration": 998
    },
    {
      "url": "https://slotscharmcasino.gb.net",
      "status": 503,
      "ok": false,
      "duration": 1006
    },
    {
      "url": "https://britsino.gb.net",
      "status": 503,
      "ok": false,
      "duration": 1048
    },
    {
      "url": "https://slotlaircasino-uk.org",
      "status": 503,
      "ok": false,
      "duration": 1052
    },
    {
      "url": "https://hotstreakcasino-uk.org",
      "status": 200,
      "ok": true,
      "duration": 155
    },
    {
      "url": "https://this-domain-is-fake-and-dead.com",
      "status": "ERROR",
      "ok": false,
      "error": "fetch failed"
    },
    {
      "url": "https://freshbet-casino.gb.net",
      "status": 503,
      "ok": false,
      "duration": 375
    },
    {
      "url": "https://prestigespincasino.gb.net",
      "status": 503,
      "ok": false,
      "duration": 386
    },
    {
      "url": "https://hotstreak-casino.org.uk",
      "status": 503,
      "ok": false,
      "duration": 397
    },
    {
      "url": "https://fresh-bet.gb.net",
      "status": 503,
      "ok": false,
      "duration": 423
    },
    {
      "url": "https://hustlescasino.gb.net",
      "status": 503,
      "ok": false,
      "duration": 435
    },
    {
      "url": "https://vibro-bet.gb.net",
      "status": 503,
      "ok": false,
      "duration": 440
    },
    {
      "url": "https://betnjet.gb.net",
      "status": 503,
      "ok": false,
      "duration": 494
    }
  ]
}