{
  "last_update": "2026-07-04T16:46:19.861Z",
  "total_sites": 34,
  "failed_count": 1,
  "data": [
    {
      "url": "https://hotstreakcasino-uk.net",
      "status": 200,
      "ok": true,
      "duration": 310
    },
    {
      "url": "https://freshbet-uk.org",
      "status": 200,
      "ok": true,
      "duration": 370
    },
    {
      "url": "https://instaspin7.com",
      "status": 200,
      "ok": true,
      "duration": 385
    },
    {
      "url": "https://tradacasino-uk.net",
      "status": 200,
      "ok": true,
      "duration": 414
    },
    {
      "url": "https://winbeastcasino.gb.net",
      "status": 503,
      "ok": false,
      "duration": 504
    },
    {
      "url": "https://britsinocasino.gb.net",
      "status": 503,
      "ok": false,
      "duration": 458
    },
    {
      "url": "https://slotscharmcasino.org.uk",
      "status": 503,
      "ok": false,
      "duration": 494
    },
    {
      "url": "https://slotlaircasino.gb.net",
      "status": 503,
      "ok": false,
      "duration": 500
    },
    {
      "url": "https://slotscharm-casino.org.uk",
      "status": 503,
      "ok": false,
      "duration": 500
    },
    {
      "url": "https://hotstreak-casino.gb.net",
      "status": 503,
      "ok": false,
      "duration": 531
    },
    {
      "url": "https://truefortune-go.com",
      "status": 200,
      "ok": true,
      "duration": 577
    },
    {
      "url": "https://true-fortune-casino.gb.net",
      "status": 503,
      "ok": false,
      "duration": 632
    },
    {
      "url": "https://freshbetcasino.gb.net",
      "status": 503,
      "ok": false,
      "duration": 636
    },
    {
      "url": "https://prestigespin-casino.org.uk",
      "status": 503,
      "ok": false,
      "duration": 677
    },
    {
      "url": "https://slotlaircasino-uk.org",
      "status": 200,
      "ok": true,
      "duration": 694
    },
    {
      "url": "https://instaspin-casino.gb.net",
      "status": 503,
      "ok": false,
      "duration": 785
    },
    {
      "url": "https://truefortune-casino.gb.net",
      "status": 503,
      "ok": false,
      "duration": 799
    },
    {
      "url": "https://instaspin-win.co.uk",
      "status": 503,
      "ok": false,
      "duration": 915
    },
    {
      "url": "https://insta-spin.gb.net",
      "status": 503,
      "ok": false,
      "duration": 943
    },
    {
      "url": "https://tradacasino-go.co.uk",
      "status": 503,
      "ok": false,
      "duration": 942
    },
    {
      "url": "https://truefortune7.co.uk",
      "status": 503,
      "ok": false,
      "duration": 965
    },
    {
      "url": "https://winbeast-casino.gb.net",
      "status": 503,
      "ok": false,
      "duration": 989
    },
    {
      "url": "https://slotscharmcasino.gb.net",
      "status": 503,
      "ok": false,
      "duration": 1062
    },
    {
      "url": "https://slotlair-casino.gb.net",
      "status": 503,
      "ok": false,
      "duration": 1065
    },
    {
      "url": "https://britsino.gb.net",
      "status": 503,
      "ok": false,
      "duration": 1078
    },
    {
      "url": "https://hotstreakcasino-uk.org",
      "status": 200,
      "ok": true,
      "duration": 180
    },
    {
      "url": "https://this-domain-is-fake-and-dead.com",
      "status": "ERROR",
      "ok": false,
      "error": "fetch failed"
    },
    {
      "url": "https://prestigespincasino.gb.net",
      "status": 503,
      "ok": false,
      "duration": 483
    },
    {
      "url": "https://fresh-bet.gb.net",
      "status": 503,
      "ok": false,
      "duration": 483
    },
    {
      "url": "https://hotstreak-casino.org.uk",
      "status": 503,
      "ok": false,
      "duration": 493
    },
    {
      "url": "https://hustlescasino.gb.net",
      "status": 503,
      "ok": false,
      "duration": 517
    },
    {
      "url": "https://freshbet-casino.gb.net",
      "status": 503,
      "ok": false,
      "duration": 541
    },
    {
      "url": "https://betnjet.gb.net",
      "status": 503,
      "ok": false,
      "duration": 596
    },
    {
      "url": "https://vibro-bet.gb.net",
      "status": 503,
      "ok": false,
      "duration": 634
    }
  ]
}