{
  "last_update": "2026-07-19T14:15:53.266Z",
  "total_sites": 34,
  "failed_count": 1,
  "data": [
    {
      "url": "https://slotscharmcasino.org.uk",
      "status": 200,
      "ok": true,
      "duration": 297
    },
    {
      "url": "https://slotlaircasino.gb.net",
      "status": 503,
      "ok": false,
      "duration": 380
    },
    {
      "url": "https://hotstreakcasino-uk.net",
      "status": 200,
      "ok": true,
      "duration": 379
    },
    {
      "url": "https://winbeastcasino.gb.net",
      "status": 503,
      "ok": false,
      "duration": 504
    },
    {
      "url": "https://slotscharm-casino.org.uk",
      "status": 503,
      "ok": false,
      "duration": 497
    },
    {
      "url": "https://freshbet-uk.org",
      "status": 200,
      "ok": true,
      "duration": 507
    },
    {
      "url": "https://prestigespin-casino.org.uk",
      "status": 503,
      "ok": false,
      "duration": 525
    },
    {
      "url": "https://britsinocasino.gb.net",
      "status": 503,
      "ok": false,
      "duration": 539
    },
    {
      "url": "https://instaspin7.com",
      "status": 200,
      "ok": true,
      "duration": 549
    },
    {
      "url": "https://hotstreak-casino.gb.net",
      "status": 503,
      "ok": false,
      "duration": 629
    },
    {
      "url": "https://tradacasino-uk.net",
      "status": 200,
      "ok": true,
      "duration": 636
    },
    {
      "url": "https://true-fortune-casino.gb.net",
      "status": 503,
      "ok": false,
      "duration": 649
    },
    {
      "url": "https://truefortune-go.com",
      "status": 200,
      "ok": true,
      "duration": 714
    },
    {
      "url": "https://freshbetcasino.gb.net",
      "status": 200,
      "ok": true,
      "duration": 773
    },
    {
      "url": "https://instaspin-casino.gb.net",
      "status": 503,
      "ok": false,
      "duration": 904
    },
    {
      "url": "https://truefortune-casino.gb.net",
      "status": 503,
      "ok": false,
      "duration": 1020
    },
    {
      "url": "https://slotlaircasino-uk.org",
      "status": 200,
      "ok": true,
      "duration": 1080
    },
    {
      "url": "https://truefortune7.co.uk",
      "status": 503,
      "ok": false,
      "duration": 1102
    },
    {
      "url": "https://instaspin-win.co.uk",
      "status": 503,
      "ok": false,
      "duration": 1268
    },
    {
      "url": "https://winbeast-casino.gb.net",
      "status": 503,
      "ok": false,
      "duration": 1277
    },
    {
      "url": "https://insta-spin.gb.net",
      "status": 503,
      "ok": false,
      "duration": 1280
    },
    {
      "url": "https://slotlair-casino.gb.net",
      "status": 503,
      "ok": false,
      "duration": 1372
    },
    {
      "url": "https://tradacasino-go.co.uk",
      "status": 503,
      "ok": false,
      "duration": 1432
    },
    {
      "url": "https://slotscharmcasino.gb.net",
      "status": 503,
      "ok": false,
      "duration": 1515
    },
    {
      "url": "https://britsino.gb.net",
      "status": 503,
      "ok": false,
      "duration": 1521
    },
    {
      "url": "https://hotstreakcasino-uk.org",
      "status": 200,
      "ok": true,
      "duration": 96
    },
    {
      "url": "https://this-domain-is-fake-and-dead.com",
      "status": "ERROR",
      "ok": false,
      "error": "fetch failed"
    },
    {
      "url": "https://prestigespincasino.gb.net",
      "status": 503,
      "ok": false,
      "duration": 371
    },
    {
      "url": "https://fresh-bet.gb.net",
      "status": 503,
      "ok": false,
      "duration": 431
    },
    {
      "url": "https://freshbet-casino.gb.net",
      "status": 503,
      "ok": false,
      "duration": 468
    },
    {
      "url": "https://hustlescasino.gb.net",
      "status": 503,
      "ok": false,
      "duration": 478
    },
    {
      "url": "https://betnjet.gb.net",
      "status": 503,
      "ok": false,
      "duration": 503
    },
    {
      "url": "https://vibro-bet.gb.net",
      "status": 503,
      "ok": false,
      "duration": 506
    },
    {
      "url": "https://hotstreak-casino.org.uk",
      "status": 503,
      "ok": false,
      "duration": 573
    }
  ]
}