{
  "last_update": "2026-07-11T10:46:58.102Z",
  "total_sites": 34,
  "failed_count": 1,
  "data": [
    {
      "url": "https://hotstreakcasino-uk.net",
      "status": 200,
      "ok": true,
      "duration": 268
    },
    {
      "url": "https://freshbetcasino.gb.net",
      "status": 200,
      "ok": true,
      "duration": 331
    },
    {
      "url": "https://freshbet-uk.org",
      "status": 200,
      "ok": true,
      "duration": 383
    },
    {
      "url": "https://tradacasino-uk.net",
      "status": 200,
      "ok": true,
      "duration": 427
    },
    {
      "url": "https://slotscharmcasino.org.uk",
      "status": 503,
      "ok": false,
      "duration": 487
    },
    {
      "url": "https://prestigespin-casino.org.uk",
      "status": 503,
      "ok": false,
      "duration": 489
    },
    {
      "url": "https://slotlaircasino.gb.net",
      "status": 503,
      "ok": false,
      "duration": 494
    },
    {
      "url": "https://winbeastcasino.gb.net",
      "status": 503,
      "ok": false,
      "duration": 556
    },
    {
      "url": "https://slotscharm-casino.org.uk",
      "status": 503,
      "ok": false,
      "duration": 498
    },
    {
      "url": "https://hotstreak-casino.gb.net",
      "status": 503,
      "ok": false,
      "duration": 578
    },
    {
      "url": "https://britsinocasino.gb.net",
      "status": 503,
      "ok": false,
      "duration": 585
    },
    {
      "url": "https://true-fortune-casino.gb.net",
      "status": 503,
      "ok": false,
      "duration": 595
    },
    {
      "url": "https://instaspin-casino.gb.net",
      "status": 503,
      "ok": false,
      "duration": 648
    },
    {
      "url": "https://slotlaircasino-uk.org",
      "status": 200,
      "ok": true,
      "duration": 654
    },
    {
      "url": "https://truefortune7.co.uk",
      "status": 503,
      "ok": false,
      "duration": 726
    },
    {
      "url": "https://instaspin7.com",
      "status": 200,
      "ok": true,
      "duration": 806
    },
    {
      "url": "https://instaspin-win.co.uk",
      "status": 503,
      "ok": false,
      "duration": 810
    },
    {
      "url": "https://truefortune-casino.gb.net",
      "status": 503,
      "ok": false,
      "duration": 814
    },
    {
      "url": "https://winbeast-casino.gb.net",
      "status": 503,
      "ok": false,
      "duration": 925
    },
    {
      "url": "https://tradacasino-go.co.uk",
      "status": 503,
      "ok": false,
      "duration": 929
    },
    {
      "url": "https://truefortune-go.com",
      "status": 200,
      "ok": true,
      "duration": 940
    },
    {
      "url": "https://insta-spin.gb.net",
      "status": 503,
      "ok": false,
      "duration": 941
    },
    {
      "url": "https://britsino.gb.net",
      "status": 503,
      "ok": false,
      "duration": 989
    },
    {
      "url": "https://slotlair-casino.gb.net",
      "status": 503,
      "ok": false,
      "duration": 1003
    },
    {
      "url": "https://slotscharmcasino.gb.net",
      "status": 503,
      "ok": false,
      "duration": 1104
    },
    {
      "url": "https://hotstreakcasino-uk.org",
      "status": 200,
      "ok": true,
      "duration": 164
    },
    {
      "url": "https://this-domain-is-fake-and-dead.com",
      "status": "ERROR",
      "ok": false,
      "error": "fetch failed"
    },
    {
      "url": "https://prestigespincasino.gb.net",
      "status": 503,
      "ok": false,
      "duration": 357
    },
    {
      "url": "https://hotstreak-casino.org.uk",
      "status": 503,
      "ok": false,
      "duration": 509
    },
    {
      "url": "https://hustlescasino.gb.net",
      "status": 503,
      "ok": false,
      "duration": 516
    },
    {
      "url": "https://fresh-bet.gb.net",
      "status": 503,
      "ok": false,
      "duration": 517
    },
    {
      "url": "https://vibro-bet.gb.net",
      "status": 503,
      "ok": false,
      "duration": 597
    },
    {
      "url": "https://betnjet.gb.net",
      "status": 503,
      "ok": false,
      "duration": 633
    },
    {
      "url": "https://freshbet-casino.gb.net",
      "status": 503,
      "ok": false,
      "duration": 635
    }
  ]
}