{
  "last_update": "2026-06-28T23:55:23.135Z",
  "total_sites": 34,
  "failed_count": 1,
  "data": [
    {
      "url": "https://winbeastcasino.gb.net",
      "status": 503,
      "ok": false,
      "duration": 655
    },
    {
      "url": "https://slotlaircasino.gb.net",
      "status": 503,
      "ok": false,
      "duration": 621
    },
    {
      "url": "https://slotscharmcasino.org.uk",
      "status": 503,
      "ok": false,
      "duration": 692
    },
    {
      "url": "https://britsinocasino.gb.net",
      "status": 503,
      "ok": false,
      "duration": 712
    },
    {
      "url": "https://prestigespin-casino.org.uk",
      "status": 503,
      "ok": false,
      "duration": 758
    },
    {
      "url": "https://slotscharm-casino.org.uk",
      "status": 503,
      "ok": false,
      "duration": 787
    },
    {
      "url": "https://hotstreak-casino.gb.net",
      "status": 503,
      "ok": false,
      "duration": 830
    },
    {
      "url": "https://hotstreakcasino-uk.net",
      "status": 503,
      "ok": false,
      "duration": 855
    },
    {
      "url": "https://true-fortune-casino.gb.net",
      "status": 503,
      "ok": false,
      "duration": 860
    },
    {
      "url": "https://freshbetcasino.gb.net",
      "status": 503,
      "ok": false,
      "duration": 866
    },
    {
      "url": "https://instaspin-casino.gb.net",
      "status": 503,
      "ok": false,
      "duration": 954
    },
    {
      "url": "https://instaspin7.com",
      "status": 503,
      "ok": false,
      "duration": 954
    },
    {
      "url": "https://freshbet-uk.org",
      "status": 503,
      "ok": false,
      "duration": 996
    },
    {
      "url": "https://tradacasino-uk.net",
      "status": 503,
      "ok": false,
      "duration": 1078
    },
    {
      "url": "https://instaspin-win.co.uk",
      "status": 503,
      "ok": false,
      "duration": 1097
    },
    {
      "url": "https://truefortune-go.com",
      "status": 503,
      "ok": false,
      "duration": 1118
    },
    {
      "url": "https://truefortune7.co.uk",
      "status": 503,
      "ok": false,
      "duration": 1124
    },
    {
      "url": "https://truefortune-casino.gb.net",
      "status": 503,
      "ok": false,
      "duration": 1150
    },
    {
      "url": "https://tradacasino-go.co.uk",
      "status": 503,
      "ok": false,
      "duration": 1161
    },
    {
      "url": "https://winbeast-casino.gb.net",
      "status": 503,
      "ok": false,
      "duration": 1198
    },
    {
      "url": "https://insta-spin.gb.net",
      "status": 503,
      "ok": false,
      "duration": 1207
    },
    {
      "url": "https://slotlair-casino.gb.net",
      "status": 503,
      "ok": false,
      "duration": 1225
    },
    {
      "url": "https://slotscharmcasino.gb.net",
      "status": 503,
      "ok": false,
      "duration": 1270
    },
    {
      "url": "https://britsino.gb.net",
      "status": 503,
      "ok": false,
      "duration": 1322
    },
    {
      "url": "https://slotlaircasino-uk.org",
      "status": 503,
      "ok": false,
      "duration": 1348
    },
    {
      "url": "https://this-domain-is-fake-and-dead.com",
      "status": "ERROR",
      "ok": false,
      "error": "fetch failed"
    },
    {
      "url": "https://hotstreak-casino.org.uk",
      "status": 503,
      "ok": false,
      "duration": 583
    },
    {
      "url": "https://prestigespincasino.gb.net",
      "status": 503,
      "ok": false,
      "duration": 627
    },
    {
      "url": "https://freshbet-casino.gb.net",
      "status": 503,
      "ok": false,
      "duration": 635
    },
    {
      "url": "https://fresh-bet.gb.net",
      "status": 503,
      "ok": false,
      "duration": 639
    },
    {
      "url": "https://hustlescasino.gb.net",
      "status": 503,
      "ok": false,
      "duration": 681
    },
    {
      "url": "https://hotstreakcasino-uk.org",
      "status": 503,
      "ok": false,
      "duration": 719
    },
    {
      "url": "https://betnjet.gb.net",
      "status": 503,
      "ok": false,
      "duration": 755
    },
    {
      "url": "https://vibro-bet.gb.net",
      "status": 503,
      "ok": false,
      "duration": 773
    }
  ]
}